logger_middleware/__init__.py
logger_middleware/middleware.py
logger_middleware-1.0.1.dist-info/licenses/LICENSE
logger_middleware-1.0.1.dist-info/METADATA
logger_middleware-1.0.1.dist-info/WHEEL
logger_middleware-1.0.1.dist-info/top_level.txt
logger_middleware-1.0.1.dist-info/RECORD
